slack_cli_hooks/__init__.py
slack_cli_hooks/py.typed
slack_cli_hooks/version.py
slack_cli_hooks/error/__init__.py
slack_cli_hooks/hooks/__init__.py
slack_cli_hooks/hooks/check_update.py
slack_cli_hooks/hooks/doctor.py
slack_cli_hooks/hooks/get_hooks.py
slack_cli_hooks/hooks/get_manifest.py
slack_cli_hooks/hooks/start.py
slack_cli_hooks/protocol/__init__.py
slack_cli_hooks/protocol/default_protocol.py
slack_cli_hooks/protocol/message_boundary_protocol.py
slack_cli_hooks/protocol/protocol.py
slack_cli_hooks-0.2.0.dist-info/licenses/LICENSE
slack_cli_hooks-0.2.0.dist-info/METADATA
slack_cli_hooks-0.2.0.dist-info/WHEEL
slack_cli_hooks-0.2.0.dist-info/top_level.txt
slack_cli_hooks-0.2.0.dist-info/RECORD
