Metadata-Version: 2.4
Name: slack_cli_hooks
Version: 0.2.0
Summary: The Slack CLI contract implementation for Bolt Python
Author-email: "Slack Technologies, LLC" <opensource@slack.com>
License: MIT
Project-URL: Source Code, https://github.com/slackapi/python-slack-hooks
Classifier: Development Status :: 2 - Pre-Alpha
Classifier: Environment :: Console
Classifier: Intended Audience :: Developers
Classifier: Topic :: Office/Business
Classifier: Topic :: Software Development
Classifier: License :: OSI Approved :: MIT License
Classifier: Programming Language :: Python
Classifier: Programming Language :: Python :: 3 :: Only
Classifier: Programming Language :: Python :: 3.9
Classifier: Programming Language :: Python :: 3.10
Classifier: Programming Language :: Python :: 3.11
Classifier: Programming Language :: Python :: 3.12
Classifier: Programming Language :: Python :: 3.13
Classifier: Programming Language :: Python :: 3.14
Classifier: Programming Language :: Python :: Implementation :: CPython
Classifier: Programming Language :: Python :: Implementation :: PyPy
Requires-Python: >=3.9
License-File: LICENSE
Requires-Dist: slack_bolt<2,>=1.18.0
Requires-Dist: packaging<26
Dynamic: license-file
